poshello/__init__.py
poshello/poshello.py
poshello-0.1.1.dist-info/METADATA
poshello-0.1.1.dist-info/WHEEL
poshello-0.1.1.dist-info/top_level.txt
poshello-0.1.1.dist-info/RECORD
